LICENSE
MANIFEST.in
README.md
pyproject.toml
setup.py
object_detection_retinanet/__init__.py
object_detection_retinanet/initializers.py
object_detection_retinanet/losses.py
object_detection_retinanet.egg-info/PKG-INFO
object_detection_retinanet.egg-info/SOURCES.txt
object_detection_retinanet.egg-info/dependency_links.txt
object_detection_retinanet.egg-info/requires.txt
object_detection_retinanet.egg-info/top_level.txt
object_detection_retinanet/backend/__init__.py
object_detection_retinanet/backend/cntk_backend.py
object_detection_retinanet/backend/common.py
object_detection_retinanet/backend/dynamic.py
object_detection_retinanet/backend/tensorflow_backend.py
object_detection_retinanet/backend/theano_backend.py
object_detection_retinanet/callbacks/__init__.py
object_detection_retinanet/callbacks/coco.py
object_detection_retinanet/callbacks/common.py
object_detection_retinanet/callbacks/eval.py
object_detection_retinanet/layers/__init__.py
object_detection_retinanet/layers/_misc.py
object_detection_retinanet/layers/filter_detections.py
object_detection_retinanet/models/__init__.py
object_detection_retinanet/models/densenet.py
object_detection_retinanet/models/mobilenet.py
object_detection_retinanet/models/resnet.py
object_detection_retinanet/models/retinanet.py
object_detection_retinanet/models/vgg.py
object_detection_retinanet/preprocessing/__init__.py
object_detection_retinanet/preprocessing/coco.py
object_detection_retinanet/preprocessing/csv_generator.py
object_detection_retinanet/preprocessing/generator.py
object_detection_retinanet/preprocessing/kitti.py
object_detection_retinanet/preprocessing/open_images.py
object_detection_retinanet/preprocessing/pascal_voc.py
object_detection_retinanet/utils/__init__.py
object_detection_retinanet/utils/anchors.py
object_detection_retinanet/utils/coco_eval.py
object_detection_retinanet/utils/colors.py
object_detection_retinanet/utils/compute_overlap.pyx
object_detection_retinanet/utils/config.py
object_detection_retinanet/utils/eval.py
object_detection_retinanet/utils/gpu.py
object_detection_retinanet/utils/image.py
object_detection_retinanet/utils/keras_version.py
object_detection_retinanet/utils/model.py
object_detection_retinanet/utils/tf_version.py
